objscale/__init__.py
objscale/_fractal_dimensions.py
objscale/_object_analysis.py
objscale/_size_distributions.py
objscale/_utils.py
objscale-0.1.6.dist-info/licenses/LICENSE
objscale-0.1.6.dist-info/METADATA
objscale-0.1.6.dist-info/WHEEL
objscale-0.1.6.dist-info/top_level.txt
objscale-0.1.6.dist-info/RECORD
