Metadata-Version: 2.4
Name: objscale
Version: 0.1.6
Summary: Object-based analysis functions for fractal dimensions and size distributions
Author-email: Thomas DeWitt <thomas.dewitt@utah.edu>
License: MIT
Project-URL: Homepage, https://github.com/thomasdewitt/objscale
Project-URL: Repository, https://github.com/thomasdewitt/objscale
Project-URL: Documentation, https://objscale.readthedocs.io
Project-URL: Issues, https://github.com/thomasdewitt/objscale/issues
Keywords: fractal,dimensions,size-distributions,object-analysis,perimeter,area
Classifier: Development Status :: 3 - Alpha
Classifier: Intended Audience :: Science/Research
Classifier: License :: OSI Approved :: MIT License
Classifier: Programming Language :: Python :: 3
Classifier: Programming Language :: Python :: 3.8
Classifier: Programming Language :: Python :: 3.9
Classifier: Programming Language :: Python :: 3.10
Classifier: Programming Language :: Python :: 3.11
Classifier: Topic :: Scientific/Engineering
Classifier: Topic :: Scientific/Engineering :: Physics
Classifier: Topic :: Scientific/Engineering :: Mathematics
Requires-Python: >=3.8
License-File: LICENSE
Requires-Dist: numpy>=1.20.0
Requires-Dist: scipy>=1.7.0
Requires-Dist: scikit-image>=0.18.0
Requires-Dist: numba>=0.56.0
Provides-Extra: dev
Requires-Dist: pytest>=6.0; extra == "dev"
Requires-Dist: pytest-cov; extra == "dev"
Requires-Dist: black; extra == "dev"
Requires-Dist: flake8; extra == "dev"
Requires-Dist: mypy; extra == "dev"
Provides-Extra: docs
Requires-Dist: sphinx>=4.0; extra == "docs"
Requires-Dist: sphinx-rtd-theme; extra == "docs"
Requires-Dist: numpydoc; extra == "docs"
Dynamic: license-file
